{
  "_fv": 17,
  "_type": "gui",
  "definition": {
    "type": 1,
    "width": 176,
    "height": 166,
    "inventoryOffsetX": 0,
    "inventoryOffsetY": 0,
    "renderBgLayer": true,
    "doesPauseGame": false,
    "components": [
      {
        "type": "label",
        "data": {
          "text": "Anvil-N Upgrader",
          "color": {
            "value": -16777216,
            "falpha": 0.0
          },
          "name": "Anvil-N Upgrader",
          "x": 177,
          "y": 39
        }
      },
      {
        "type": "inputslot",
        "data": {
          "inputLimit": {
            "value": "CUSTOM:Updateritem"
          },
          "id": 0,
          "disableStackInteraction": false,
          "dropItemsWhenNotBound": true,
          "name": "Slot #0",
          "x": 141,
          "y": 48
        }
      },
      {
        "type": "inputslot",
        "data": {
          "inputLimit": {
            "value": "CUSTOM:NetheriteN"
          },
          "id": 1,
          "disableStackInteraction": false,
          "dropItemsWhenNotBound": true,
          "name": "Slot #1",
          "x": 168,
          "y": 75
        }
      },
      {
        "type": "inputslot",
        "data": {
          "inputLimit": {
            "value": ""
          },
          "id": 2,
          "disableStackInteraction": false,
          "dropItemsWhenNotBound": true,
          "name": "Slot #2",
          "x": 213,
          "y": 75
        }
      },
      {
        "type": "outputslot",
        "data": {
          "id": 3,
          "disableStackInteraction": false,
          "dropItemsWhenNotBound": true,
          "name": "Slot #3",
          "x": 258,
          "y": 75
        }
      },
      {
        "type": "button",
        "data": {
          "text": "Upgrade",
          "onClick": {
            "name": "AnvilNProcced"
          },
          "width": 70,
          "height": 20,
          "name": "Upgrade",
          "x": 182,
          "y": 98
        }
      }
    ]
  }
}