{
  "variants": {
    "facing=south": {
      "model": "negativen:block/chiseled_quartz_n_block"
    },
    "facing=north": {
      "model": "negativen:block/chiseled_quartz_n_block"
    },
    "facing=east": {
      "model": "negativen:block/chiseled_quartz_n_block",
      "x": 90
    },
    "facing=west": {
      "model": "negativen:block/chiseled_quartz_n_block",
      "x": 90
    },
    "facing=up": {
      "model": "negativen:block/chiseled_quartz_n_block",
      "x": 90,
      "y": 90
    },
    "facing=down": {
      "model": "negativen:block/chiseled_quartz_n_block",
      "x": 90,
      "y": 90
    }
  }
}